cpu-gpu-design/cpu.v
// cpu.v - minimal single-cycle 16-bit CPU
// 8 registers (R0 hardwired to 0), 256-word instruction & data memory.
module cpu (
    input  wire        clk,
    input  wire        rst,
    output reg         halted
);
    reg [15:0] imem [0:255];   // instruction memory
    reg [15:0] dmem [0:255];   // data memory
    reg [15:0] regs [0:7];     // register file
    reg [7:0]  pc;
    wire [15:0] R1 = regs[1];   // for waveform viewing
    wire [15:0] R2 = regs[2];

    // ---- instruction decode (combinational) ----
    wire [15:0] inst  = imem[pc];
    wire [3:0]  op    = inst[15:12];
    wire [2:0]  rd    = inst[11:9];
    wire [2:0]  rs    = inst[8:6];
    wire [2:0]  rt    = inst[5:3];
    wire [8:0]  imm9  = inst[8:0];
    wire [5:0]  imm6  = inst[5:0];
    wire [11:0] imm12 = inst[11:0];

    wire signed [15:0] sext9 = {{7{imm9[8]}}, imm9};
    wire signed [15:0] sext6 = {{10{imm6[5]}}, imm6};

    // register reads (R0 always reads 0)
    wire [15:0] vs = (rs==0) ? 16'd0 : regs[rs];
    wire [15:0] vt = (rt==0) ? 16'd0 : regs[rt];
    wire [15:0] vd = (rd==0) ? 16'd0 : regs[rd];

    integer i;
    always @(posedge clk or posedge rst) begin
        if (rst) begin
            pc <= 0; halted <= 0;
            for (i=0;i<8;i=i+1) regs[i] <= 0;
        end else if (!halted) begin
            case (op)
                4'h0: pc <= pc+1;                                        // NOP
                4'h1: begin if(rd!=0) regs[rd] <= vs + vt; pc<=pc+1; end // ADD  rd,rs,rt
                4'h2: begin if(rd!=0) regs[rd] <= vs - vt; pc<=pc+1; end // SUB
                4'h3: begin if(rd!=0) regs[rd] <= vs & vt; pc<=pc+1; end // AND
                4'h4: begin if(rd!=0) regs[rd] <= vs | vt; pc<=pc+1; end // OR
                4'h5: begin if(rd!=0) regs[rd] <= vs ^ vt; pc<=pc+1; end // XOR
                4'h6: begin if(rd!=0) regs[rd] <= dmem[vs[7:0]]; pc<=pc+1; end // LW  rd,[rs]
                4'h7: begin dmem[vs[7:0]] <= vt; pc<=pc+1; end           // SW  [rs],rt
                4'h8: begin if(rd!=0) regs[rd] <= sext9; pc<=pc+1; end   // LI  rd,imm9
                4'h9: begin if(rd!=0) regs[rd] <= vs + sext6; pc<=pc+1; end // ADDI rd,rs,imm6
                4'hA: begin if(vd==0) pc <= pc + sext9[7:0]; else pc<=pc+1; end // BEQZ rd,off (rel to this instr)
                4'hB: pc <= imm12[7:0];                                  // JMP addr
                4'hF: halted <= 1;                                       // HLT
                default: pc <= pc+1;
            endcase
        end
    end
endmodule

cpu-gpu-design/cpu_tb.v
`timescale 1ns/1ps
module cpu_tb;
    reg clk = 0, rst = 1;
    wire halted;
    integer i;
    cpu uut (.clk(clk), .rst(rst), .halted(halted));
    always #5 clk = ~clk;               // 100 MHz

    initial begin
        $dumpfile("cpu.vcd"); $dumpvars(0, cpu_tb);
        $readmemh("program.hex", uut.imem);
        #12 rst = 0;                     // release reset
        wait (halted == 1); #10;
        $display("== CPU halted ==");
        for (i=0;i<8;i=i+1)
            $display("R%0d = %0d (0x%04h)", i, uut.regs[i], uut.regs[i]);
        $display("dmem[0] = %0d (0x%04h)", uut.dmem[0], uut.dmem[0]);
        $finish;
    end
    initial begin #10000 $display("TIMEOUT (no HLT)"); $finish; end
endmodule

cpu.vcd
$date
	Sat Jun 27 13:33:58 2026
$end
$version
	Icarus Verilog
$end
$timescale
	1ps
$end
$scope module cpu_tb $end
$var wire 1 ! halted $end
$var reg 1 " clk $end
$var reg 1 # rst $end
$var integer 32 $ i [31:0] $end
$scope module uut $end
$var wire 16 % R1 [15:0] $end
$var wire 16 & R2 [15:0] $end
$var wire 1 " clk $end
$var wire 16 ' inst [15:0] $end
$var wire 1 # rst $end
$var wire 16 ( vt [15:0] $end
$var wire 16 ) vs [15:0] $end
$var wire 16 * vd [15:0] $end
$var wire 16 + sext9 [15:0] $end
$var wire 16 , sext6 [15:0] $end
$var wire 3 - rt [2:0] $end
$var wire 3 . rs [2:0] $end
$var wire 3 / rd [2:0] $end
$var wire 4 0 op [3:0] $end
$var wire 9 1 imm9 [8:0] $end
$var wire 6 2 imm6 [5:0] $end
$var wire 12 3 imm12 [11:0] $end
$var reg 1 ! halted $end
$var reg 8 4 pc [7:0] $end
$var integer 32 5 i [31:0] $end
$upscope $end
$upscope $end
$enddefinitions $end
$comment Show the parameter values. $end
$dumpall
$end
#0
$dumpvars
bx 5
bx 4
bx 3
bx 2
bx 1
bx 0
bx /
bx .
bx -
bx ,
bx +
bx *
bx )
bx (
bx '
bx &
bx %
bx $
1#
0"
x!
$end
#5000
b0 *
b0 )
b0 (
b1000 0
b1 /
b0 .
b0 -
b0 +
b0 1
b0 ,
b0 2
b1000000000 3
b0 &
b0 %
0!
b1000001000000000 '
b0 4
b1000 5
1"
#10000
0"
#12000
0#
#15000
b10 /
b101 +
b101 1
b101 ,
b101 2
b10000000101 3
b1000010000000101 '
b1 4
1"
#20000
0"
#25000
b1010 0
b100 +
b100 1
b100 ,
b100 2
b10000000100 3
b101 *
b1010010000000100 '
b10 4
b101 &
1"
#30000
0"
#35000
b0 *
b101 (
b1 0
b1 /
b1 .
b10 -
b1010000 +
b1010000 1
b10000 ,
b10000 2
b1001010000 3
b1001001010000 '
b11 4
1"
#40000
0"
#45000
b0 (
b1001 0
b10 /
b10 .
b111 -
b10111111 +
b10111111 1
b1111111111111111 ,
b111111 2
b10010111111 3
b101 )
b101 *
b1001010010111111 '
b100 4
b101 %
1"
#50000
0"
#55000
b1011 0
b0 /
b0 .
b0 -
b10 +
b10 1
b10 ,
b10 2
b10 3
b0 )
b0 *
b1011000000000010 '
b101 4
b100 &
1"
#60000
0"
#65000
b100 *
b1010 0
b10 /
b100 +
b100 1
b100 ,
b100 2
b10000000100 3
b1010010000000100 '
b10 4
1"
#70000
0"
#75000
b101 *
b101 )
b100 (
b1 0
b1 /
b1 .
b10 -
b1010000 +
b1010000 1
b10000 ,
b10000 2
b1001010000 3
b1001001010000 '
b11 4
1"
#80000
0"
#85000
b0 (
b1001 0
b10 /
b10 .
b111 -
b10111111 +
b10111111 1
b1111111111111111 ,
b111111 2
b10010111111 3
b100 )
b100 *
b1001010010111111 '
b100 4
b1001 %
1"
#90000
0"
#95000
b1011 0
b0 /
b0 .
b0 -
b10 +
b10 1
b10 ,
b10 2
b10 3
b0 )
b0 *
b1011000000000010 '
b101 4
b11 &
1"
#100000
0"
#105000
b11 *
b1010 0
b10 /
b100 +
b100 1
b100 ,
b100 2
b10000000100 3
b1010010000000100 '
b10 4
1"
#110000
0"
#115000
b1001 *
b1001 )
b11 (
b1 0
b1 /
b1 .
b10 -
b1010000 +
b1010000 1
b10000 ,
b10000 2
b1001010000 3
b1001001010000 '
b11 4
1"
#120000
0"
#125000
b0 (
b1001 0
b10 /
b10 .
b111 -
b10111111 +
b10111111 1
b1111111111111111 ,
b111111 2
b10010111111 3
b11 )
b11 *
b1001010010111111 '
b100 4
b1100 %
1"
#130000
0"
#135000
b1011 0
b0 /
b0 .
b0 -
b10 +
b10 1
b10 ,
b10 2
b10 3
b0 )
b0 *
b1011000000000010 '
b101 4
b10 &
1"
#140000
0"
#145000
b10 *
b1010 0
b10 /
b100 +
b100 1
b100 ,
b100 2
b10000000100 3
b1010010000000100 '
b10 4
1"
#150000
0"
#155000
b1100 *
b1100 )
b10 (
b1 0
b1 /
b1 .
b10 -
b1010000 +
b1010000 1
b10000 ,
b10000 2
b1001010000 3
b1001001010000 '
b11 4
1"
#160000
0"
#165000
b0 (
b1001 0
b10 /
b10 .
b111 -
b10111111 +
b10111111 1
b1111111111111111 ,
b111111 2
b10010111111 3
b10 )
b10 *
b1001010010111111 '
b100 4
b1110 %
1"
#170000
0"
#175000
b1011 0
b0 /
b0 .
b0 -
b10 +
b10 1
b10 ,
b10 2
b10 3
b0 )
b0 *
b1011000000000010 '
b101 4
b1 &
1"
#180000
0"
#185000
b1 *
b1010 0
b10 /
b100 +
b100 1
b100 ,
b100 2
b10000000100 3
b1010010000000100 '
b10 4
1"
#190000
0"
#195000
b1110 *
b1110 )
b1 (
b1 0
b1 /
b1 .
b10 -
b1010000 +
b1010000 1
b10000 ,
b10000 2
b1001010000 3
b1001001010000 '
b11 4
1"
#200000
0"
#205000
b0 (
b1001 0
b10 /
b10 .
b111 -
b10111111 +
b10111111 1
b1111111111111111 ,
b111111 2
b10010111111 3
b1 )
b1 *
b1001010010111111 '
b100 4
b1111 %
1"
#210000
0"
#215000
b1011 0
b0 /
b0 .
b0 -
b10 +
b10 1
b10 ,
b10 2
b10 3
b0 )
b0 *
b1011000000000010 '
b101 4
b0 &
1"
#220000
0"
#225000
b1010 0
b10 /
b100 +
b100 1
b100 ,
b100 2
b10000000100 3
b1010010000000100 '
b10 4
1"
#230000
0"
#235000
b1111 (
b111 0
b0 /
b1 -
b1000 +
b1000 1
b1000 ,
b1000 2
b1000 3
b111000000001000 '
b110 4
1"
#240000
0"
#245000
b0 (
b1111 0
b0 -
b0 +
b0 1
b0 ,
b0 2
b0 3
b1111000000000000 '
b111 4
1"
#250000
0"
#255000
1!
1"
#260000
0"
#265000
1"
b1000 $
